infralib/__init__.py
infralib/infraio.py
infralib/simulator.py
infralib/envs/__init__.py
infralib/envs/base.py
infralib/envs/simple.py
infralib/models/__init__.py
infralib/models/base.py
infralib/models/budget.py
infralib/models/cost.py
infralib/models/dynamics.py
infralib/models/hierarchy.py
infralib/models/metadata.py
infralib/visualize/__init__.py
infralib/visualize/dashboard.py
infralib/visualize/network.py
infralib/visualize/plots.py
infralib/visualize/simulator_plots.py
infralib-0.1.0.dist-info/METADATA
infralib-0.1.0.dist-info/WHEEL
infralib-0.1.0.dist-info/licenses/LICENSE
infralib-0.1.0.dist-info/RECORD
