Metadata-Version: 2.4
Name: infralib
Version: 0.1.0
Summary: Infrastructure simulation library for reinforcement learning and optimization
Project-URL: Homepage, https://infralib.github.io/
Project-URL: Repository, https://github.com/pthangeda/InfraLib
Project-URL: Issues, https://github.com/pthangeda/InfraLib/issues
Project-URL: Documentation, https://infralib.readthedocs.io/
Author-email: InfraLib Team <contact@prny.me>
License: MIT
License-File: LICENSE
Classifier: Development Status :: 3 - Alpha
Classifier: Intended Audience :: Developers
Classifier: Intended Audience :: Science/Research
Classifier: License :: OSI Approved :: MIT License
Classifier: Programming Language :: Python :: 3
Classifier: Programming Language :: Python :: 3.12
Classifier: Topic :: Scientific/Engineering :: Artificial Intelligence
Requires-Python: >=3.12
Requires-Dist: dash>=3.2.0
Requires-Dist: folium>=0.20.0
Requires-Dist: geopandas>=1.1.1
Requires-Dist: gymnasium>=1.0.0
Requires-Dist: ipykernel>=6.20.0
Requires-Dist: matplotlib>=3.7.2
Requires-Dist: networkx>=3.5
Requires-Dist: numba>=0.61.2
Requires-Dist: numpy>=1.25.2
Requires-Dist: osmnx>=2.0.5
Requires-Dist: pandas>=2.0.0
Requires-Dist: plotly>=6.2.0
Requires-Dist: pytest-cov>=6.2.1
Requires-Dist: pytest>=8.4.1
Requires-Dist: pyyaml>=6.0
Requires-Dist: rich>=14.1.0
Requires-Dist: ruff>=0.12.8
Requires-Dist: scipy>=1.10.0
Requires-Dist: seaborn>=0.12.2
Requires-Dist: stable-baselines3>=2.0.0
Requires-Dist: streamlit>=1.48.0
Requires-Dist: tensorboard>=2.20.0
Requires-Dist: tensordict>=0.9.1
Requires-Dist: torch>=2.0.0
Requires-Dist: torchrl>=0.9.2
Requires-Dist: tqdm>=4.60.0
Requires-Dist: wandb>=0.21.1
Provides-Extra: dev
Requires-Dist: pre-commit>=3.5.0; extra == 'dev'
Requires-Dist: pytest-cov>=4.0.0; extra == 'dev'
Requires-Dist: pytest>=8.0.0; extra == 'dev'
Requires-Dist: ruff>=0.6.0; extra == 'dev'
Provides-Extra: docs
Requires-Dist: sphinx-autodoc-typehints>=1.24.0; extra == 'docs'
Requires-Dist: sphinx-rtd-theme>=2.0.0; extra == 'docs'
Requires-Dist: sphinx>=7.0.0; extra == 'docs'
